kds/__init__.py
kds/db.py
kds/feature_selection.py
kds/ml.py
kds/preprocess.py
kds/raw.py
kds/util.py
kidaura_ds-0.1.0.dist-info/METADATA
kidaura_ds-0.1.0.dist-info/WHEEL
kidaura_ds-0.1.0.dist-info/top_level.txt
kidaura_ds-0.1.0.dist-info/RECORD
