Metadata-Version: 2.1
Name: kidaura-ds
Version: 0.1.0
Summary: Kidaura data science module
Home-page: UNKNOWN
Author: Paras Sharmaa
Author-email: paras@kidaura.com
License: MIT
Platform: UNKNOWN
Requires-Dist: p-tqdm
Requires-Dist: pandas
Requires-Dist: numpy
Requires-Dist: scipy
Requires-Dist: scikit-learn
Requires-Dist: sympy
Requires-Dist: boto3
